README.md
setup.cfg
setup.py
bin/rsc
riverstone_cli/__init__.py
riverstone_cli/__main__.py
riverstone_cli/test_main.py
riverstone_cli.egg-info/PKG-INFO
riverstone_cli.egg-info/SOURCES.txt
riverstone_cli.egg-info/dependency_links.txt
riverstone_cli.egg-info/not-zip-safe
riverstone_cli.egg-info/requires.txt
riverstone_cli.egg-info/top_level.txt
riverstone_cli/commands/__init__.py
riverstone_cli/commands/base.py
riverstone_cli/commands/commands.py
riverstone_cli/commands/issue/__init__.py
riverstone_cli/commands/issue/issue.py
riverstone_cli/commands/wireframe/__init__.py
riverstone_cli/commands/wireframe/wireframe.py
riverstone_cli/common/__init__.py
riverstone_cli/common/constants.py
riverstone_cli/common/utils.py