Metadata-Version: 1.0
Name: riverstone-cli
Version: 0.0.4
Summary: Riverstone CLI for Riverstone employees.
Home-page: https://riverstone.io/
Author: Riverstone Software, LLC
Author-email: info@riverstone.io
License: Apache License (2.0)
Platform: UNKNOWN
